django_plugin_datasette/__init__.py
django_plugin_datasette-0.2.dist-info/LICENSE
django_plugin_datasette-0.2.dist-info/METADATA
django_plugin_datasette-0.2.dist-info/WHEEL
django_plugin_datasette-0.2.dist-info/entry_points.txt
django_plugin_datasette-0.2.dist-info/top_level.txt
django_plugin_datasette-0.2.dist-info/RECORD
