Metadata-Version: 2.1
Name: django-plugin-datasette
Version: 0.2
Summary: Django plugin to run Datasette inside of Django
Author: Simon Willison
License: Apache-2.0
Project-URL: Homepage, https://github.com/simonw/django-plugin-datasette
Project-URL: Changelog, https://github.com/simonw/django-plugin-datasette/releases
Project-URL: Issues, https://github.com/simonw/django-plugin-datasette/issues
Project-URL: CI, https://github.com/simonw/django-plugin-datasette/actions
Classifier: License :: OSI Approved :: Apache Software License
License-File: LICENSE
Requires-Dist: django
Requires-Dist: djp >=0.3
Requires-Dist: datasette
Provides-Extra: test
Requires-Dist: pytest ; extra == 'test'
Requires-Dist: pytest-django ; extra == 'test'
Requires-Dist: pytest-asyncio ; extra == 'test'
Requires-Dist: httpx ; extra == 'test'
